duotalk/__init__.py
duotalk/__main__.py
duotalk/dual_voice_agents.py
duotalk/enhanced_youtube_agent.py
duotalk/four_agents_duotalk.py
duotalk/py.typed
duotalk/quick.py
duotalk/agents/__init__.py
duotalk/agents/persona_agent.py
duotalk/agents/voice_agent.py
duotalk/cli/__init__.py
duotalk/cli/__main__.py
duotalk/cli/main.py
duotalk/cli/main_simple.py
duotalk/cli/simple.py
duotalk/cli/voice_cli.py
duotalk/config/__init__.py
duotalk/config/enhanced_config.py
duotalk/core/__init__.py
duotalk/core/builder.py
duotalk/core/config.py
duotalk/core/convenience.py
duotalk/core/convenience_youtube.py
duotalk/core/demo.py
duotalk/core/runner.py
duotalk/core/session.py
duotalk/core/tts_handler.py
duotalk/core/voice_runner.py
duotalk/core/youtube_summarizer.py
duotalk/modes/__init__.py
duotalk/personas/__init__.py
duotalk/stats/__init__.py
duotalk-1.0.7.dist-info/licenses/LICENSE
duotalk-1.0.7.dist-info/METADATA
duotalk-1.0.7.dist-info/WHEEL
duotalk-1.0.7.dist-info/entry_points.txt
duotalk-1.0.7.dist-info/top_level.txt
duotalk-1.0.7.dist-info/RECORD
