Metadata-Version: 2.4
Name: duotalk
Version: 1.0.7
Summary: Advanced multi-agent voice conversation system with customizable personas and modes
Author-email: Abhyuday Patel <patelabhyuday09@gmail.com>
License: MIT
Project-URL: Homepage, https://github.com/AbhyudayPatel/DuoTalk
Project-URL: Repository, https://github.com/AbhyudayPatel/DuoTalk
Project-URL: Documentation, https://duotalk.readthedocs.io
Project-URL: Issues, https://github.com/AbhyudayPatel/DuoTalk/issues
Keywords: voice,ai,conversation,agents,livekit,gemini
Classifier: Development Status :: 4 - Beta
Classifier: Intended Audience :: Developers
Classifier: License :: OSI Approved :: MIT License
Classifier: Programming Language :: Python :: 3
Classifier: Programming Language :: Python :: 3.8
Classifier: Programming Language :: Python :: 3.9
Classifier: Programming Language :: Python :: 3.10
Classifier: Programming Language :: Python :: 3.11
Classifier: Programming Language :: Python :: 3.12
Classifier: Topic :: Software Development :: Libraries :: Python Modules
Classifier: Topic :: Multimedia :: Sound/Audio :: Speech
Classifier: Topic :: Scientific/Engineering :: Artificial Intelligence
Requires-Python: >=3.8
License-File: LICENSE
Requires-Dist: livekit-agents>=1.2.0
Requires-Dist: livekit-plugins-google>=0.8.0
Requires-Dist: python-dotenv>=1.0.0
Requires-Dist: pydantic>=2.0.0
Requires-Dist: typer>=0.9.0
Requires-Dist: rich>=13.0.0
Requires-Dist: asyncio-mqtt>=0.16.0
Requires-Dist: structlog>=23.0.0
Requires-Dist: yt-dlp>=2023.1.6
Requires-Dist: requests>=2.28.0
Requires-Dist: livekit-plugins-cartesia>=0.2.0
Requires-Dist: edge-tts>=7.0.0
Requires-Dist: pygame>=2.0.0
Requires-Dist: google-generativeai>=0.8.0
Provides-Extra: dev
Requires-Dist: pytest>=7.0.0; extra == "dev"
Requires-Dist: pytest-asyncio>=0.21.0; extra == "dev"
Requires-Dist: black>=23.0.0; extra == "dev"
Requires-Dist: ruff>=0.1.0; extra == "dev"
Requires-Dist: mypy>=1.0.0; extra == "dev"
Requires-Dist: pre-commit>=3.0.0; extra == "dev"
Provides-Extra: docs
Requires-Dist: mkdocs>=1.5.0; extra == "docs"
Requires-Dist: mkdocs-material>=9.0.0; extra == "docs"
Requires-Dist: mkdocstrings[python]>=0.23.0; extra == "docs"
Dynamic: license-file
